<?xml version="1.0" encoding="utf-8"?>
<key id="9a9d264d-424f-43ca-be21-05398d84c987" version="1">
  <creationDate>2025-11-11T08:47:13.7392654Z</creationDate>
  <activationDate>2025-11-11T08:47:13.7354156Z</activationDate>
  <expirationDate>2026-02-09T08:47:13.7354156Z</expirationDate>
  <descriptor deserializerType="Microsoft.AspNetCore.DataProtection.AuthenticatedEncryption.ConfigurationModel.AuthenticatedEncryptorDescriptorDeserializer, Microsoft.AspNetCore.DataProtection, Version=8.0.0.0, Culture=neutral, PublicKeyToken=adb9793829ddae60">
    <descriptor>
      <encryption algorithm="AES_256_CBC" />
      <validation algorithm="HMACSHA256" />
      <masterKey p4:requiresEncryption="true" xmlns:p4="http://schemas.asp.net/2015/03/dataProtection">
        <!-- Warning: the key below is in an unencrypted form. -->
        <value>hcIsvuEjQj//n6nYDW4DL7nAsux8h3eZW1Hse1Rq91L/C+5TgDwnz3sglrr3NqTkp0qfCws7txQ8T0+Kzzrc8A==</value>
      </masterKey>
    </descriptor>
  </descriptor>
</key>